<annotation>
	<folder>images</folder>
	<filename>China_Drone_000558.jpg</filename>
	<size>
		<width>512</width>
		<height>512</height>
		<depth>3</depth>
	</size>
	<segmented>0</segmented>
	<object>
		<name>D00</name>
		<pose>Unspecified</pose>
		<truncated>0</truncated>
		<difficult>0</difficult>
		<bndbox>
			<xmin>74</xmin>
			<ymin>139</ymin>
			<xmax>100</xmax>
			<ymax>236</ymax>
		</bndbox>
	</object>
	<object>
		<name>D10</name>
		<pose>Unspecified</pose>
		<truncated>0</truncated>
		<difficult>0</difficult>
		<bndbox>
			<xmin>35</xmin>
			<ymin>425</ymin>
			<xmax>146</xmax>
			<ymax>450</ymax>
		</bndbox>
	</object>
</annotation>