<annotation>
	<folder>images</folder>
	<filename>China_Drone_001515.jpg</filename>
	<size>
		<width>512</width>
		<height>512</height>
		<depth>3</depth>
	</size>
	<segmented>0</segmented>
	<object>
		<name>D00</name>
		<pose>Unspecified</pose>
		<truncated>0</truncated>
		<difficult>0</difficult>
		<bndbox>
			<xmin>99</xmin>
			<ymin>28</ymin>
			<xmax>122</xmax>
			<ymax>142</ymax>
		</bndbox>
	</object>
	<object>
		<name>D00</name>
		<pose>Unspecified</pose>
		<truncated>0</truncated>
		<difficult>0</difficult>
		<bndbox>
			<xmin>91</xmin>
			<ymin>343</ymin>
			<xmax>115</xmax>
			<ymax>461</ymax>
		</bndbox>
	</object>
</annotation>