<annotation>
	<folder>images</folder>
	<filename>China_MotorBike_001755.jpg</filename>
	<size>
		<width>512</width>
		<height>512</height>
		<depth>3</depth>
	</size>
	<segmented>0</segmented>
	<object>
		<name>D10</name>
		<pose>Unspecified</pose>
		<truncated>1</truncated>
		<difficult>0</difficult>
		<bndbox>
			<xmin>164</xmin>
			<ymin>251</ymin>
			<xmax>512</xmax>
			<ymax>306</ymax>
		</bndbox>
	</object>
	<object>
		<name>D10</name>
		<pose>Unspecified</pose>
		<truncated>1</truncated>
		<difficult>0</difficult>
		<bndbox>
			<xmin>1</xmin>
			<ymin>333</ymin>
			<xmax>295</xmax>
			<ymax>374</ymax>
		</bndbox>
	</object>
</annotation>