<annotation>
  <folder>images</folder>
  <filename>Norway_001968.jpg</filename>
  <size>
    <width>3643</width>
    <height>2041</height>
    <depth />
  </size>
  <segmented>0</segmented>
  <object>
    <name>D00</name>
    <truncated>0</truncated>
    <occluded>0</occluded>
    <difficult>0</difficult>
    <bndbox>
      <xmin>1444.39</xmin>
      <ymin>1136.52</ymin>
      <xmax>1478.9</xmax>
      <ymax>1159.14</ymax>
    </bndbox>
    <attributes>
      <attribute>
        <name>rotation</name>
        <value>0.0</value>
      </attribute>
    </attributes>
  </object>
  <object>
    <name>D00</name>
    <truncated>0</truncated>
    <occluded>0</occluded>
    <difficult>0</difficult>
    <bndbox>
      <xmin>1252.79</xmin>
      <ymin>1121.05</ymin>
      <xmax>1381.32</xmax>
      <ymax>1207.93</ymax>
    </bndbox>
    <attributes>
      <attribute>
        <name>rotation</name>
        <value>0.0</value>
      </attribute>
    </attributes>
  </object>
</annotation>