<annotation>
  <folder>images</folder>
  <filename>Norway_003148.jpg</filename>
  <size>
    <width>3643</width>
    <height>2041</height>
    <depth />
  </size>
  <segmented>0</segmented>
  <object>
    <name>D00</name>
    <truncated>0</truncated>
    <occluded>0</occluded>
    <difficult>0</difficult>
    <bndbox>
      <xmin>1493.6</xmin>
      <ymin>1459.54</ymin>
      <xmax>1538.19</xmax>
      <ymax>1522.71</ymax>
    </bndbox>
    <attributes>
      <attribute>
        <name>rotation</name>
        <value>0.0</value>
      </attribute>
    </attributes>
  </object>
  <object>
    <name>D10</name>
    <truncated>0</truncated>
    <occluded>0</occluded>
    <difficult>0</difficult>
    <bndbox>
      <xmin>725.53</xmin>
      <ymin>1649.04</ymin>
      <xmax>1545.62</xmax>
      <ymax>1684.96</ymax>
    </bndbox>
    <attributes>
      <attribute>
        <name>rotation</name>
        <value>0.0</value>
      </attribute>
    </attributes>
  </object>
  <object>
    <name>D00</name>
    <truncated>0</truncated>
    <occluded>0</occluded>
    <difficult>0</difficult>
    <bndbox>
      <xmin>1477.37</xmin>
      <ymin>1500.41</ymin>
      <xmax>1499.79</xmax>
      <ymax>1566.06</ymax>
    </bndbox>
    <attributes>
      <attribute>
        <name>rotation</name>
        <value>0.0</value>
      </attribute>
    </attributes>
  </object>
  <object>
    <name>D00</name>
    <truncated>0</truncated>
    <occluded>0</occluded>
    <difficult>0</difficult>
    <bndbox>
      <xmin>1532.0</xmin>
      <ymin>1562.34</ymin>
      <xmax>1560.48</xmax>
      <ymax>1652.76</ymax>
    </bndbox>
    <attributes>
      <attribute>
        <name>rotation</name>
        <value>0.0</value>
      </attribute>
    </attributes>
  </object>
</annotation>