<annotation>
  <folder>images</folder>
  <filename>Norway_001433.jpg</filename>
  <size>
    <width>3643</width>
    <height>2041</height>
    <depth />
  </size>
  <segmented>0</segmented>
  <object>
    <name>D00</name>
    <truncated>0</truncated>
    <occluded>0</occluded>
    <difficult>0</difficult>
    <bndbox>
      <xmin>1562.69</xmin>
      <ymin>1216.18</ymin>
      <xmax>1620.2</xmax>
      <ymax>1240.97</ymax>
    </bndbox>
    <attributes>
      <attribute>
        <name>rotation</name>
        <value>0.0</value>
      </attribute>
    </attributes>
  </object>
  <object>
    <name>D20</name>
    <truncated>0</truncated>
    <occluded>0</occluded>
    <difficult>0</difficult>
    <bndbox>
      <xmin>560.3</xmin>
      <ymin>1266.4</ymin>
      <xmax>1804.28</xmax>
      <ymax>2032.37</ymax>
    </bndbox>
    <attributes>
      <attribute>
        <name>rotation</name>
        <value>0.0</value>
      </attribute>
    </attributes>
  </object>
  <object>
    <name>D00</name>
    <truncated>0</truncated>
    <occluded>0</occluded>
    <difficult>0</difficult>
    <bndbox>
      <xmin>1326.66</xmin>
      <ymin>1096.18</ymin>
      <xmax>1525.0</xmax>
      <ymax>1205.27</ymax>
    </bndbox>
    <attributes>
      <attribute>
        <name>rotation</name>
        <value>0.0</value>
      </attribute>
    </attributes>
  </object>
  <object>
    <name>D00</name>
    <truncated>0</truncated>
    <occluded>0</occluded>
    <difficult>0</difficult>
    <bndbox>
      <xmin>1037.08</xmin>
      <ymin>1127.92</ymin>
      <xmax>1325.66</xmax>
      <ymax>1257.83</ymax>
    </bndbox>
    <attributes>
      <attribute>
        <name>rotation</name>
        <value>0.0</value>
      </attribute>
    </attributes>
  </object>
</annotation>