<annotation>
  <folder>images</folder>
  <filename>Norway_004526.jpg</filename>
  <size>
    <width>3643</width>
    <height>2041</height>
    <depth />
  </size>
  <segmented>0</segmented>
  <object>
    <name>D00</name>
    <truncated>0</truncated>
    <occluded>0</occluded>
    <difficult>0</difficult>
    <bndbox>
      <xmin>1573.1</xmin>
      <ymin>1242.4</ymin>
      <xmax>1701.46</xmax>
      <ymax>1415.44</ymax>
    </bndbox>
    <attributes>
      <attribute>
        <name>rotation</name>
        <value>0.0</value>
      </attribute>
    </attributes>
  </object>
</annotation>