<annotation>
  <folder>images</folder>
  <filename>Norway_002029.jpg</filename>
  <size>
    <width>3650</width>
    <height>2044</height>
    <depth />
  </size>
  <segmented>0</segmented>
  <object>
    <name>D00</name>
    <truncated>0</truncated>
    <occluded>0</occluded>
    <difficult>0</difficult>
    <bndbox>
      <xmin>371.31</xmin>
      <ymin>2001.0</ymin>
      <xmax>462.27</xmax>
      <ymax>2038.78</ymax>
    </bndbox>
    <attributes>
      <attribute>
        <name>rotation</name>
        <value>0.0</value>
      </attribute>
    </attributes>
  </object>
  <object>
    <name>D00</name>
    <truncated>0</truncated>
    <occluded>0</occluded>
    <difficult>0</difficult>
    <bndbox>
      <xmin>1362.03</xmin>
      <ymin>1949.59</ymin>
      <xmax>1417.74</xmax>
      <ymax>1998.25</ymax>
    </bndbox>
    <attributes>
      <attribute>
        <name>rotation</name>
        <value>0.0</value>
      </attribute>
    </attributes>
  </object>
  <object>
    <name>D00</name>
    <truncated>0</truncated>
    <occluded>0</occluded>
    <difficult>0</difficult>
    <bndbox>
      <xmin>326.69</xmin>
      <ymin>1807.09</ymin>
      <xmax>544.65</xmax>
      <ymax>1980.43</ymax>
    </bndbox>
    <attributes>
      <attribute>
        <name>rotation</name>
        <value>0.0</value>
      </attribute>
    </attributes>
  </object>
</annotation>