<annotation>
  <folder>images</folder>
  <filename>Norway_007602.jpg</filename>
  <size>
    <width>3650</width>
    <height>2044</height>
    <depth />
  </size>
  <segmented>0</segmented>
  <object>
    <name>D10</name>
    <truncated>0</truncated>
    <occluded>0</occluded>
    <difficult>0</difficult>
    <bndbox>
      <xmin>1404.5</xmin>
      <ymin>1477.6</ymin>
      <xmax>1594.97</xmax>
      <ymax>1499.89</ymax>
    </bndbox>
    <attributes>
      <attribute>
        <name>rotation</name>
        <value>0.0</value>
      </attribute>
    </attributes>
  </object>
  <object>
    <name>D00</name>
    <truncated>0</truncated>
    <occluded>0</occluded>
    <difficult>0</difficult>
    <bndbox>
      <xmin>947.37</xmin>
      <ymin>1525.2</ymin>
      <xmax>1084.53</xmax>
      <ymax>1725.82</ymax>
    </bndbox>
    <attributes>
      <attribute>
        <name>rotation</name>
        <value>0.0</value>
      </attribute>
    </attributes>
  </object>
  <object>
    <name>D00</name>
    <truncated>0</truncated>
    <occluded>0</occluded>
    <difficult>0</difficult>
    <bndbox>
      <xmin>1124.82</xmin>
      <ymin>1166.48</ymin>
      <xmax>1148.27</xmax>
      <ymax>1192.69</ymax>
    </bndbox>
    <attributes>
      <attribute>
        <name>rotation</name>
        <value>0.0</value>
      </attribute>
    </attributes>
  </object>
  <object>
    <name>D00</name>
    <truncated>0</truncated>
    <occluded>0</occluded>
    <difficult>0</difficult>
    <bndbox>
      <xmin>1180.69</xmin>
      <ymin>1205.1</ymin>
      <xmax>1198.62</xmax>
      <ymax>1289.25</ymax>
    </bndbox>
    <attributes>
      <attribute>
        <name>rotation</name>
        <value>0.0</value>
      </attribute>
    </attributes>
  </object>
  <object>
    <name>D00</name>
    <truncated>0</truncated>
    <occluded>0</occluded>
    <difficult>0</difficult>
    <bndbox>
      <xmin>359.3</xmin>
      <ymin>1354.01</ymin>
      <xmax>661.35</xmax>
      <ymax>1491.31</ymax>
    </bndbox>
    <attributes>
      <attribute>
        <name>rotation</name>
        <value>0.0</value>
      </attribute>
    </attributes>
  </object>
  <object>
    <name>D00</name>
    <truncated>0</truncated>
    <occluded>0</occluded>
    <difficult>0</difficult>
    <bndbox>
      <xmin>728.88</xmin>
      <ymin>1718.87</ymin>
      <xmax>961.38</xmax>
      <ymax>2044.0</ymax>
    </bndbox>
    <attributes>
      <attribute>
        <name>rotation</name>
        <value>0.0</value>
      </attribute>
    </attributes>
  </object>
  <object>
    <name>D00</name>
    <truncated>0</truncated>
    <occluded>0</occluded>
    <difficult>0</difficult>
    <bndbox>
      <xmin>1079.96</xmin>
      <ymin>1287.54</ymin>
      <xmax>1200.14</xmax>
      <ymax>1531.86</ymax>
    </bndbox>
    <attributes>
      <attribute>
        <name>rotation</name>
        <value>0.0</value>
      </attribute>
    </attributes>
  </object>
  <object>
    <name>D00</name>
    <truncated>0</truncated>
    <occluded>0</occluded>
    <difficult>0</difficult>
    <bndbox>
      <xmin>103.58</xmin>
      <ymin>1499.89</ymin>
      <xmax>357.58</xmax>
      <ymax>1652.63</ymax>
    </bndbox>
    <attributes>
      <attribute>
        <name>rotation</name>
        <value>0.0</value>
      </attribute>
    </attributes>
  </object>
  <object>
    <name>D40</name>
    <truncated>0</truncated>
    <occluded>0</occluded>
    <difficult>0</difficult>
    <bndbox>
      <xmin>841.2</xmin>
      <ymin>1616.58</ymin>
      <xmax>903.77</xmax>
      <ymax>1656.3</ymax>
    </bndbox>
    <attributes>
      <attribute>
        <name>rotation</name>
        <value>0.0</value>
      </attribute>
    </attributes>
  </object>
  <object>
    <name>D10</name>
    <truncated>0</truncated>
    <occluded>0</occluded>
    <difficult>0</difficult>
    <bndbox>
      <xmin>982.28</xmin>
      <ymin>1374.61</ymin>
      <xmax>1150.47</xmax>
      <ymax>1393.48</ymax>
    </bndbox>
    <attributes>
      <attribute>
        <name>rotation</name>
        <value>0.0</value>
      </attribute>
    </attributes>
  </object>
  <object>
    <name>D00</name>
    <truncated>0</truncated>
    <occluded>0</occluded>
    <difficult>0</difficult>
    <bndbox>
      <xmin>0.0</xmin>
      <ymin>1546.23</ymin>
      <xmax>232.3</xmax>
      <ymax>1654.35</ymax>
    </bndbox>
    <attributes>
      <attribute>
        <name>rotation</name>
        <value>0.0</value>
      </attribute>
    </attributes>
  </object>
  <object>
    <name>D10</name>
    <truncated>0</truncated>
    <occluded>0</occluded>
    <difficult>0</difficult>
    <bndbox>
      <xmin>669.93</xmin>
      <ymin>1532.5</ymin>
      <xmax>1085.25</xmax>
      <ymax>1559.96</ymax>
    </bndbox>
    <attributes>
      <attribute>
        <name>rotation</name>
        <value>0.0</value>
      </attribute>
    </attributes>
  </object>
</annotation>