<annotation>
  <folder>images</folder>
  <filename>Norway_007143.jpg</filename>
  <size>
    <width>3643</width>
    <height>2041</height>
    <depth />
  </size>
  <segmented>0</segmented>
  <object>
    <name>D00</name>
    <truncated>0</truncated>
    <occluded>0</occluded>
    <difficult>0</difficult>
    <bndbox>
      <xmin>1198.89</xmin>
      <ymin>1168.18</ymin>
      <xmax>1337.57</xmax>
      <ymax>1295.01</ymax>
    </bndbox>
    <attributes>
      <attribute>
        <name>rotation</name>
        <value>0.0</value>
      </attribute>
    </attributes>
  </object>
  <object>
    <name>D00</name>
    <truncated>0</truncated>
    <occluded>0</occluded>
    <difficult>0</difficult>
    <bndbox>
      <xmin>1349.04</xmin>
      <ymin>1164.78</ymin>
      <xmax>1450.6</xmax>
      <ymax>1220.1</ymax>
    </bndbox>
    <attributes>
      <attribute>
        <name>rotation</name>
        <value>0.0</value>
      </attribute>
    </attributes>
  </object>
  <object>
    <name>D00</name>
    <truncated>0</truncated>
    <occluded>0</occluded>
    <difficult>0</difficult>
    <bndbox>
      <xmin>1467.0</xmin>
      <ymin>1251.0</ymin>
      <xmax>1602.0</xmax>
      <ymax>1461.0</ymax>
    </bndbox>
    <attributes>
      <attribute>
        <name>rotation</name>
        <value>0.0</value>
      </attribute>
    </attributes>
  </object>
  <object>
    <name>D00</name>
    <truncated>0</truncated>
    <occluded>0</occluded>
    <difficult>0</difficult>
    <bndbox>
      <xmin>1496.2</xmin>
      <ymin>1220.08</ymin>
      <xmax>1628.16</xmax>
      <ymax>1283.47</ymax>
    </bndbox>
    <attributes>
      <attribute>
        <name>rotation</name>
        <value>0.0</value>
      </attribute>
    </attributes>
  </object>
  <object>
    <name>D00</name>
    <truncated>0</truncated>
    <occluded>0</occluded>
    <difficult>0</difficult>
    <bndbox>
      <xmin>1262.31</xmin>
      <ymin>1223.25</ymin>
      <xmax>1362.6</xmax>
      <ymax>1365.11</ymax>
    </bndbox>
    <attributes>
      <attribute>
        <name>rotation</name>
        <value>0.0</value>
      </attribute>
    </attributes>
  </object>
  <object>
    <name>D00</name>
    <truncated>0</truncated>
    <occluded>0</occluded>
    <difficult>0</difficult>
    <bndbox>
      <xmin>1234.0</xmin>
      <ymin>1421.0</ymin>
      <xmax>1363.0</xmax>
      <ymax>1784.0</ymax>
    </bndbox>
    <attributes>
      <attribute>
        <name>rotation</name>
        <value>0.0</value>
      </attribute>
    </attributes>
  </object>
</annotation>