<annotation>
  <folder>images</folder>
  <filename>Norway_003220.jpg</filename>
  <size>
    <width>3650</width>
    <height>2044</height>
    <depth />
  </size>
  <segmented>0</segmented>
  <object>
    <name>D40</name>
    <truncated>0</truncated>
    <occluded>0</occluded>
    <difficult>0</difficult>
    <bndbox>
      <xmin>2665.88</xmin>
      <ymin>1623.46</ymin>
      <xmax>2882.12</xmax>
      <ymax>1697.25</ymax>
    </bndbox>
    <attributes>
      <attribute>
        <name>rotation</name>
        <value>0.0</value>
      </attribute>
    </attributes>
  </object>
  <object>
    <name>D40</name>
    <truncated>0</truncated>
    <occluded>0</occluded>
    <difficult>0</difficult>
    <bndbox>
      <xmin>1150.89</xmin>
      <ymin>1155.7</ymin>
      <xmax>1189.7</xmax>
      <ymax>1167.18</ymax>
    </bndbox>
    <attributes>
      <attribute>
        <name>rotation</name>
        <value>0.0</value>
      </attribute>
    </attributes>
  </object>
  <object>
    <name>D00</name>
    <truncated>0</truncated>
    <occluded>0</occluded>
    <difficult>0</difficult>
    <bndbox>
      <xmin>1460.85</xmin>
      <ymin>1120.88</ymin>
      <xmax>1513.48</xmax>
      <ymax>1207.29</ymax>
    </bndbox>
    <attributes>
      <attribute>
        <name>rotation</name>
        <value>0.0</value>
      </attribute>
    </attributes>
  </object>
  <object>
    <name>D40</name>
    <truncated>0</truncated>
    <occluded>0</occluded>
    <difficult>0</difficult>
    <bndbox>
      <xmin>1265.37</xmin>
      <ymin>1147.06</ymin>
      <xmax>1294.15</xmax>
      <ymax>1160.47</ymax>
    </bndbox>
    <attributes>
      <attribute>
        <name>rotation</name>
        <value>0.0</value>
      </attribute>
    </attributes>
  </object>
  <object>
    <name>D20</name>
    <truncated>0</truncated>
    <occluded>0</occluded>
    <difficult>0</difficult>
    <bndbox>
      <xmin>3009.12</xmin>
      <ymin>1518.8</ymin>
      <xmax>3650.0</xmax>
      <ymax>2038.78</ymax>
    </bndbox>
    <attributes>
      <attribute>
        <name>rotation</name>
        <value>0.0</value>
      </attribute>
    </attributes>
  </object>
  <object>
    <name>D20</name>
    <truncated>0</truncated>
    <occluded>0</occluded>
    <difficult>0</difficult>
    <bndbox>
      <xmin>2078.94</xmin>
      <ymin>1439.82</ymin>
      <xmax>2650.43</xmax>
      <ymax>1633.75</ymax>
    </bndbox>
    <attributes>
      <attribute>
        <name>rotation</name>
        <value>0.0</value>
      </attribute>
    </attributes>
  </object>
  <object>
    <name>D40</name>
    <truncated>0</truncated>
    <occluded>0</occluded>
    <difficult>0</difficult>
    <bndbox>
      <xmin>164.95</xmin>
      <ymin>1599.54</ymin>
      <xmax>245.42</xmax>
      <ymax>1645.04</ymax>
    </bndbox>
    <attributes>
      <attribute>
        <name>rotation</name>
        <value>0.0</value>
      </attribute>
    </attributes>
  </object>
  <object>
    <name>D40</name>
    <truncated>0</truncated>
    <occluded>0</occluded>
    <difficult>0</difficult>
    <bndbox>
      <xmin>1204.06</xmin>
      <ymin>1150.9</ymin>
      <xmax>1247.69</xmax>
      <ymax>1167.66</ymax>
    </bndbox>
    <attributes>
      <attribute>
        <name>rotation</name>
        <value>0.0</value>
      </attribute>
    </attributes>
  </object>
</annotation>