<annotation>
	<folder>images</folder>
	<filename>United_States_004602.jpg</filename>
	<size>
		<width>640</width>
		<height>640</height>
		<depth>3</depth>
	</size>
	<segmented>0</segmented>
	<object>
		<name>D00</name>
		<pose>Unspecified</pose>
		<truncated>0</truncated>
		<difficult>0</difficult>
		<bndbox>
			<xmin>214</xmin>
			<ymin>373</ymin>
			<xmax>305</xmax>
			<ymax>635</ymax>
		</bndbox>
	</object>
	<object>
		<name>D00</name>
		<pose>Unspecified</pose>
		<truncated>0</truncated>
		<difficult>0</difficult>
		<bndbox>
			<xmin>359</xmin>
			<ymin>435</ymin>
			<xmax>507</xmax>
			<ymax>638</ymax>
		</bndbox>
	</object>
	<object>
		<name>D10</name>
		<pose>Unspecified</pose>
		<truncated>0</truncated>
		<difficult>0</difficult>
		<bndbox>
			<xmin>351</xmin>
			<ymin>443</ymin>
			<xmax>469</xmax>
			<ymax>466</ymax>
		</bndbox>
	</object>
</annotation>